{"specversion":"1.0","id":"e3d6f3ea-b7e3-4771-8df3-072ae739f2fa","source":"https://minikube.sigs.k8s.io/","type":"io.k8s.sigs.minikube.step","datacontenttype":"application/json","data":{"currentstep":"0","message":"* minikube v1.36.0 on Ubuntu 24.04","name":"Initial Minikube Setup","totalsteps":"19"}}
{"specversion":"1.0","id":"be64258d-fb92-4850-b91f-4dd5cebce24c","source":"https://minikube.sigs.k8s.io/","type":"io.k8s.sigs.minikube.step","datacontenttype":"application/json","data":{"currentstep":"1","message":"* Using the docker driver based on user configuration","name":"Selecting Driver","totalsteps":"19"}}
{"specversion":"1.0","id":"e8a86be0-10ca-4c25-8fd5-953d08ef15ed","source":"https://minikube.sigs.k8s.io/","type":"io.k8s.sigs.minikube.step","datacontenttype":"application/json","data":{"currentstep":"3","message":"* Starting \"minikube\" primary control-plane node in \"minikube\" cluster","name":"Starting Node","totalsteps":"19"}}
{"specversion":"1.0","id":"0044e870-34ee-43d7-a1b9-cf149632aae8","source":"https://minikube.sigs.k8s.io/","type":"io.k8s.sigs.minikube.step","datacontenttype":"application/json","data":{"currentstep":"5","message":"* Pulling base image v0.0.47 ...","name":"Pulling Base Image","totalsteps":"19"}}
{"specversion":"1.0","id":"7af5d307-d661-48e6-9383-411a490edb3f","source":"https://minikube.sigs.k8s.io/","type":"io.k8s.sigs.minikube.step","datacontenttype":"application/json","data":{"currentstep":"8","message":"* Creating docker container (CPUs=2, Memory=2200MB) ...","name":"Creating Container","totalsteps":"19"}}
{"specversion":"1.0","id":"d35e6b6f-93fa-464d-9145-f7e8ba8151a5","source":"https://minikube.sigs.k8s.io/","type":"io.k8s.sigs.minikube.error","datacontenttype":"application/json","data":{"message":"X Docker is nearly out of disk space, which may cause deployments to fail! (85% of capacity). You can pass '--force' to skip this check."}}
{"specversion":"1.0","id":"812c81e9-fcef-4e86-b3f4-a08956b8dec4","source":"https://minikube.sigs.k8s.io/","type":"io.k8s.sigs.minikube.error","datacontenttype":"application/json","data":{"message":"* Suggestion: \n\n    Try one or more of the following to free up space on the device:\n    \n    1. Run \"docker system prune\" to remove unused Docker data (optionally with \"-a\")\n    2. Increase the storage allocated to Docker for Desktop by clicking on:\n    Docker icon \u003e Preferences \u003e Resources \u003e Disk Image Size\n    3. Run \"minikube ssh -- docker system prune\" if using the Docker container runtime"}}
{"specversion":"1.0","id":"32dc8962-ba60-420e-add2-242f62f96555","source":"https://minikube.sigs.k8s.io/","type":"io.k8s.sigs.minikube.error","datacontenttype":"application/json","data":{"message":"* Related issue: https://github.com/kubernetes/minikube/issues/9024"}}
{"specversion":"1.0","id":"93909c6f-3ae5-405e-a84b-b07239bdfc47","source":"https://minikube.sigs.k8s.io/","type":"io.k8s.sigs.minikube.step","datacontenttype":"application/json","data":{"currentstep":"11","message":"* Preparing Kubernetes v1.33.1 on Docker 28.1.1 ...","name":"Preparing Kubernetes","totalsteps":"19"}}
{"specversion":"1.0","id":"b0acf78a-8da5-42fc-82f7-f9868871ccb7","source":"https://minikube.sigs.k8s.io/","type":"io.k8s.sigs.minikube.step","datacontenttype":"application/json","data":{"currentstep":"12","message":"- Generating certificates and keys ...","name":"Generating certificates","totalsteps":"19"}}
{"specversion":"1.0","id":"54a4be50-ccd2-4616-ab32-9a16caf7cf1d","source":"https://minikube.sigs.k8s.io/","type":"io.k8s.sigs.minikube.step","datacontenttype":"application/json","data":{"currentstep":"13","message":"- Booting up control plane ...","name":"Booting control plane","totalsteps":"19"}}
{"specversion":"1.0","id":"ebad972d-ba49-49d4-a5b6-4e8b53df5c38","source":"https://minikube.sigs.k8s.io/","type":"io.k8s.sigs.minikube.step","datacontenttype":"application/json","data":{"currentstep":"14","message":"- Configuring RBAC rules ...","name":"Configuring RBAC rules","totalsteps":"19"}}
{"specversion":"1.0","id":"92dcbeb4-305e-4df9-a8b4-b4181a88f074","source":"https://minikube.sigs.k8s.io/","type":"io.k8s.sigs.minikube.step","datacontenttype":"application/json","data":{"currentstep":"15","message":"* Configuring bridge CNI (Container Networking Interface) ...","name":"Configuring CNI","totalsteps":"19"}}
{"specversion":"1.0","id":"281192a3-2272-41f3-9a2f-0533e37583bd","source":"https://minikube.sigs.k8s.io/","type":"io.k8s.sigs.minikube.step","datacontenttype":"application/json","data":{"currentstep":"17","message":"* Verifying Kubernetes components...","name":"Verifying Kubernetes","totalsteps":"19"}}
{"specversion":"1.0","id":"54858704-215a-4a7d-977c-9cfa7ac868e3","source":"https://minikube.sigs.k8s.io/","type":"io.k8s.sigs.minikube.step","datacontenttype":"application/json","data":{"currentstep":"18","message":"* Enabled addons: storage-provisioner, default-storageclass","name":"Enabling Addons","totalsteps":"19"}}
{"specversion":"1.0","id":"2d01fe38-85d9-4e23-95f1-958f6fd5b2e3","source":"https://minikube.sigs.k8s.io/","type":"io.k8s.sigs.minikube.error","datacontenttype":"application/json","data":{"message":"! /usr/local/bin/kubectl is version 1.31.0, which may have incompatibilities with Kubernetes 1.33.1."}}
{"specversion":"1.0","id":"058d9eea-9a15-4cd1-9914-c262d40cf8d1","source":"https://minikube.sigs.k8s.io/","type":"io.k8s.sigs.minikube.step","datacontenttype":"application/json","data":{"currentstep":"19","message":"* Done! kubectl is now configured to use \"minikube\" cluster and \"default\" namespace by default","name":"Done","totalsteps":"19"}}
